geofence_validator/__init__.py
geofence_validator/__main__.py
geofence_validator/core.py
geofence_validator/errors.py
geofence_validator/logger.py
geofence_validator/policy.py
geofence_validator/resolver.py
geofence_validator/data/ip_ranges.csv
geofence_validator-0.1.0.dist-info/licenses/LICENSE
geofence_validator-0.1.0.dist-info/METADATA
geofence_validator-0.1.0.dist-info/WHEEL
geofence_validator-0.1.0.dist-info/entry_points.txt
geofence_validator-0.1.0.dist-info/top_level.txt
geofence_validator-0.1.0.dist-info/RECORD
