Metadata-Version: 2.4
Name: geofence-validator
Version: 0.1.0
Summary: A zero-dependency, deterministic, and high-performance Python library for IP-based geofence validation.
Author-email: Sooraj K R <soorajkr03@gmail.com>
Maintainer-email: Sooraj K R <soorajkr03@gmail.com>
License-Expression: MIT
Project-URL: Homepage, https://github.com/SunK3R/geofence-validator
Project-URL: Repository, https://github.com/SunK3R/geofence-validator
Project-URL: Bug Tracker, https://github.com/SunK3R/geofence-validator/issues
Project-URL: Documentation, https://github.com/SunK3R/geofence-validator/blob/main/README.md
Keywords: geofence,geoip,security,validation,network,acl,ipaddress
Classifier: Development Status :: 5 - Production/Stable
Classifier: Intended Audience :: Developers
Classifier: Operating System :: OS Independent
Classifier: Programming Language :: Python
Classifier: Programming Language :: Python :: 3
Classifier: Programming Language :: Python :: 3.9
Classifier: Programming Language :: Python :: 3.10
Classifier: Programming Language :: Python :: 3.11
Classifier: Programming Language :: Python :: 3.12
Classifier: Programming Language :: Python :: Implementation :: CPython
Classifier: Topic :: Security
Classifier: Topic :: Software Development :: Libraries :: Python Modules
Classifier: Topic :: System :: Networking
Classifier: Typing :: Typed
Requires-Python: >=3.9
License-File: LICENSE
Provides-Extra: rich
Requires-Dist: rich>=13.0.0; extra == "rich"
Provides-Extra: dev
Requires-Dist: pytest>=7.0; extra == "dev"
Requires-Dist: pytest-cov>=5.0.0; extra == "dev"
Requires-Dist: ruff>=0.1; extra == "dev"
Requires-Dist: mypy>=1.6; extra == "dev"
Requires-Dist: requests>=2.31.0; extra == "dev"
Requires-Dist: python-dotenv>=1.0.0; extra == "dev"
Requires-Dist: rich>=13.0.0; extra == "dev"
Requires-Dist: build; extra == "dev"
Requires-Dist: twine; extra == "dev"
Dynamic: license-file
